gxkent/__init__.py
gxkent/gxkent.py
gxkent/proportion_expectation_maker.py
gxkent-0.2.8.dist-info/LICENSE.txt
gxkent-0.2.8.dist-info/METADATA
gxkent-0.2.8.dist-info/WHEEL
gxkent-0.2.8.dist-info/top_level.txt
gxkent-0.2.8.dist-info/RECORD
