Metadata-Version: 2.1
Name: gxkent
Version: 0.2.8
Summary: A way to use Great Expectations in Google Collab and other notebook environments.
Home-page: https://github.com/careset/GXKent
Author: Fred Trotter
Author-email: fred.trotter@careset.com
License: LICENSE.txt
Classifier: Development Status :: 3 - Alpha
Classifier: Intended Audience :: Developers
Classifier: License :: OSI Approved :: MIT License
Classifier: Programming Language :: Python :: 3
Classifier: Programming Language :: Python :: 3.6
Classifier: Programming Language :: Python :: 3.7
Classifier: Programming Language :: Python :: 3.8
Classifier: Programming Language :: Python :: 3.9
Requires-Python: >=3.6
License-File: LICENSE.txt
